Metadata-Version: 1.1
Name: coolbpf
Version: 0.1.0
Summary: cool libbpf compile collections
Home-page: https://github.com/aliyun/coolbpf
Author: liaozhaoyan
Author-email: zhaoyan.liao@linux.alibaba.com
License: MIT
Keywords: linux kernel trace
Platform: UNKNOWN
Classifier: Topic :: System :: Operating System Kernels :: Linux
Classifier: Programming Language :: Python
Classifier: Programming Language :: Python :: 2
Classifier: Programming Language :: Python :: 2.7
Classifier: Programming Language :: Python :: 3
Classifier: Programming Language :: Python :: 3.5
Classifier: Programming Language :: Python :: 3.6
Classifier: Programming Language :: Python :: 3.7
Classifier: Programming Language :: Python :: 3.8
Classifier: Programming Language :: Python :: 3.9
Classifier: Programming Language :: Python :: 3.10
Classifier: Programming Language :: Python :: Implementation :: PyPy
